[
  {
    "sku": "DRS-FLORAL-M",
    "product_name": "碎花收腰连衣裙 M",
    "warehouse": "广州仓",
    "available_stock": 42,
    "safety_stock": 80,
    "locked_stock": 18
  },
  {
    "sku": "TEE-COTTON-WHT-L",
    "product_name": "纯棉基础白T恤 L",
    "warehouse": "广州仓",
    "available_stock": 260,
    "safety_stock": 120,
    "locked_stock": 35
  },
  {
    "sku": "SKT-DENIM-S",
    "product_name": "高腰牛仔半身裙 S",
    "warehouse": "佛山仓",
    "available_stock": 15,
    "safety_stock": 60,
    "locked_stock": 10
  },
  {
    "sku": "HOODIE-GRY-L",
    "product_name": "灰色短款卫衣 L",
    "warehouse": "佛山仓",
    "available_stock": 22,
    "safety_stock": 100,
    "locked_stock": 8
  }
]
